extented_ws/__init__.py
extented_ws/exceptions.py
extented_ws/protocols.py
extented_ws/server.py
extented_ws/message/__init__.py
extented_ws/message/handler.py
extented_ws/message/observer.py
extented_ws/message/types.py
extented_ws-0.1.4.dist-info/LICENSE
extented_ws-0.1.4.dist-info/METADATA
extented_ws-0.1.4.dist-info/WHEEL
extented_ws-0.1.4.dist-info/top_level.txt
extented_ws-0.1.4.dist-info/RECORD
