Metadata-Version: 2.1
Name: extented-ws
Version: 0.1.4
Summary: This is a web socket wrapper for handling JSON messages in the 'handler' way
Author-email: Sergei Ivanov <dexsperpro@gmail.com>
License: MIT License
Project-URL: Homepage, https://gitlab.com/ts-workflow/template/tbot-ts-example-sockets-webapp
Classifier: Intended Audience :: Developers
Classifier: Operating System :: OS Independent
Classifier: Programming Language :: Python :: 3.11
Requires-Python: >=3.11
License-File: LICENSE
Requires-Dist: websockets >=11.0.3
Requires-Dist: aiogram >=3.1.1
